[
  {
    "is-primary-key": "False",
    "name": "ObjectId",
    "width": "50",
    "data-type": "varchar",
    "default-value": "null",
    "is-nullable": "True"
  },
  {
    "is-primary-key": "True",
    "name": "PanelOrderId",
    "width": "50",
    "data-type": "varchar",
    "default-value": "null",
    "is-nullable": "False"
  },
  {
    "is-primary-key": "False",
    "name": "ReportNo",
    "width": "20",
    "data-type": "varchar",
    "default-value": "null",
    "is-nullable": "True"
  },
  {
    "is-primary-key": "False",
    "name": "PanelId",
    "width": "11",
    "data-type": "int",
    "default-value": "0",
    "is-nullable": "False"
  },
  {
    "is-primary-key": "False",
    "name": "PanelName",
    "width": "100",
    "data-type": "varchar",
    "default-value": "null",
    "is-nullable": "True"
  },
  {
    "is-primary-key": "False",
    "name": "ResultCode",
    "width": "50",
    "data-type": "varchar",
    "default-value": "null",
    "is-nullable": "True"
  },
  {
    "is-primary-key": "False",
    "name": "PanelOrderBatchId",
    "width": "11",
    "data-type": "int",
    "default-value": "0",
    "is-nullable": "True"
  },
  {
    "is-primary-key": "False",
    "name": "Acknowledged",
    "width": "1",
    "data-type": "tinyint",
    "default-value": "0",
    "is-nullable": "False"
  },
  {
    "is-primary-key": "False",
    "name": "AcknowledgedDate",
    "width": "3",
    "data-type": "datetime",
    "default-value": "null",
    "is-nullable": "True"
  },
  {
    "is-primary-key": "False",
    "name": "AcknowledgedTime",
    "width": "3",
    "data-type": "datetime",
    "default-value": "null",
    "is-nullable": "True"
  },
  {
    "is-primary-key": "False",
    "name": "AcceptedById",
    "width": "11",
    "data-type": "int",
    "default-value": "0",
    "is-nullable": "False"
  },
  {
    "is-primary-key": "False",
    "name": "Accepted",
    "width": "1",
    "data-type": "tinyint",
    "default-value": "0",
    "is-nullable": "False"
  },
  {
    "is-primary-key": "False",
    "name": "AcceptedDate",
    "width": "3",
    "data-type": "datetime",
    "default-value": "null",
    "is-nullable": "True"
  },
  {
    "is-primary-key": "False",
    "name": "AcceptedTime",
    "width": "3",
    "data-type": "datetime",
    "default-value": "null",
    "is-nullable": "True"
  },
  {
    "is-primary-key": "False",
    "name": "AcknowledgedById",
    "width": "11",
    "data-type": "int",
    "default-value": "0",
    "is-nullable": "False"
  },
  {
    "is-primary-key": "False",
    "name": "OrderedById",
    "width": "11",
    "data-type": "int",
    "default-value": "0",
    "is-nullable": "False"
  },
  {
    "is-primary-key": "False",
    "name": "OrderDate",
    "width": "3",
    "data-type": "datetime",
    "default-value": "null",
    "is-nullable": "True"
  },
  {
    "is-primary-key": "False",
    "name": "OrderTime",
    "width": "3",
    "data-type": "datetime",
    "default-value": "null",
    "is-nullable": "True"
  },
  {
    "is-primary-key": "False",
    "name": "Comment",
    "width": "500",
    "data-type": "varchar",
    "default-value": "null",
    "is-nullable": "True"
  },
  {
    "is-primary-key": "False",
    "name": "AssignedToId",
    "width": "11",
    "data-type": "int",
    "default-value": "0",
    "is-nullable": "False"
  }
]